<내용>
	<위치>
		<서명>역주 능엄경언해</서명>
		<단계명>역주 능엄경언해 제1</단계명>
		<단계명>[운허]Ⅱ. 정종분(正宗分)○첫째 사마타를 말하여 진심을 알게 하다 ①</단계명>
		<단계명>제2절 마음이 지금 어디에 있는가?</단계명>
		<기사제목>2. 마음이 몸 밖에 있는 것 같다 1</기사제목>
	</위치>

	<본문>
		<기사>
			<구결><원본위치 imgFile="P15_NE_e01_v001_052b.jpg">능엄경언해 권1:52ㄴ</원본위치>二. 在外 二○一. 徵〔경문〕 阿難이 稽首와 而白佛言호 我聞如來ㅅ 如是法音고 悟知我心이 實居身外콰다 所以者何오 譬如燈光이 然於室中면 是燈이 必能先照室內고 從其室門야 後及庭際리니 一切衆生이 不見身中고 獨見身外호미 亦如燈光이 居在室外야 不能照室 니 是義ㅣ 必明야 將無所惑야 同佛了義호니 得無妄耶ㅣ가</구결>
		</기사>
		<기사>
			<언해>〔경문〕 <원본위치 imgFile="P15_NE_e01_v001_052b.jpg">능엄경언해 권1:52ㄴ</원본위치>阿難이 머리 조와 부텻긔 오 내 如來ㅅ 이러신 <원본위치 imgFile="P15_NE_e01_v001_053a.jpg">능엄경언해 권1:53ㄱ</원본위치>法音을 듣고 내 미 實로 몸 밧긔 이쇼 알와다 엇뎨어뇨 가비건댄 燈光이 집 안해 혀면 이 燈이 반기 能히 몬져 집 안 비취오 그 집 門 조차 後에   미츠리니 一切 衆生이 몸 안 보디 몯고 몸 밧 보미  燈光이 집 밧긔 이셔 能히 지블 비취디 몯 니 이 디 반기 가  疑心 업서 부텻 了義 호니 아니 외니가 <협주>【了義  그테 다 디라】</협주></언해>
		</기사>
		<기사>
			<번역문>〔경문〕 <sent lang="역주" n="2" page="v001_052b" type="main"/>아난이 머리를 조아리고 부처님께 사뢰되, <sent lang="역주" n="3" page="v001_052b" type="main"/>“제가 여래의 이러하신 <sent lang="역주" n="1" page="v001_053a" type="main"/>법음을 듣잡고 제 마음이 실로 몸 밖에 있음을 알았습니다. <sent lang="역주" n="2" page="v001_053a" type="main"/>어찌된 것인가(=왜냐하면) 견주건댄 등불이(=등불을) 집 안에 켜면 이 등이 반드시 능히 먼저 집 안을 비추고, <sent lang="역주" n="3" page="v001_053a" type="main"/>〈다음에〉 그 집 문을 따라(=통하여) 뒤에 〈있는〉 뜰 가에 미칠 것이니, <sent lang="역주" n="4" page="v001_053a" type="main"/>일체 중생이 몸 안을 보지 못하고 몸 바깥만 보는 것은, 또 〈마치〉 등불이 집 밖에 있어서 능히 집을(=방을) 비추지 못하듯 하니, <sent lang="역주" n="5" page="v001_053a" type="main"/>이〈런〉 뜻이(=이치가) 반드시 밝아(=분명하여) 장차 의심이 없어 부처님의 요의와 같으니 그르지 않은 것입니까? <sent lang="역주" n="6" page="v001_053a" type="main"/><협주>【요의는 한 끝에 다달았다는 뜻이다.】</협주>.”고 하였다.</번역문>
		</기사>
		<기사>
			<구결>〔주해〕 因破非內야 復生妄計야 謂心이 在外라 요로 爲決了義니라</구결>
			</저자정보>
				<한글>세조(조선)</한글>
				<한자>世祖(朝鮮)</한자>
				<출판일>1461년(세조 7)</출판일>
			</저자정보>
		</기사>
		<기사>
			<언해>〔주해〕 안히 아니라 허샤 因야 다시 거즛 혜 내야 닐오 미 밧긔 잇다 호로 決了義 사니라</언해>
			</저자정보>
				<한글>간경도감</한글>
				<한자>刊經都監</한자>
				<출판일>1462년(세조 8)</출판일>
			</저자정보>
		</기사>
		<기사>
			<번역문>〔주해〕 <sent lang="역주" n="7" page="v001_053a" type="anno"/>안이 아니라고 허심을 인하여 다시 거짓 헤아림을 내어 <sent lang="역주" n="8" page="v001_053a" type="anno"/>이르되 마음이 밖에 있다 한 것으로 결요의를 삼은 것이다.</번역문>
			</저자정보>
				<한글>김영배</한글>
				<한자>金英培</한자>
				<출판일>1996년 9월 22일</출판일>
			</저자정보>
		</기사>
	</본문>

	<주석목록>
		<주석><주석번호>001</주석번호><주석내용>조와：조아려.</주석내용></주석>
		<주석><주석번호>002</주석번호><주석내용>알와다：알았습니다. 「-와~과」 1인칭 활용.</주석내용></주석>
		<주석><주석번호>003</주석번호><주석내용>엇뎨어뇨：어찌된 것인가? 무슨 까닭인가?</주석내용></주석>
		<주석><주석번호>004</주석번호><주석내용>혀면：켜면. 「혀-」.</주석내용></주석>
		<주석><주석번호>005</주석번호><주석내용>비취오：비추고.</주석내용></주석>
		<주석><주석번호>006</주석번호><주석내용> ：뜰 가에.</주석내용></주석>
		<주석><주석번호>007</주석번호><주석내용>미츠리니：미칠 것이니.</주석내용></주석>
		<주석><주석번호>008</주석번호><주석내용>밧：밖만.</주석내용></주석>
		<주석><주석번호>009</주석번호><주석내용>비취디：비추지.</주석내용></주석>
		<주석><주석번호>010</주석번호><주석내용>디：뜻이.</주석내용></주석>
		<주석><주석번호>011</주석번호><주석내용>호니：같으니.</주석내용></주석>
		<주석><주석번호>012</주석번호><주석내용>아니 외니가：그르지 않은 것입니까?</주석내용></주석>
		<주석><주석번호>013</주석번호><주석내용>요의：불법의 이치를 말하여 다한 것.</주석내용></주석>
		<주석><주석번호>014</주석번호><주석내용>허샤：허심을.</주석내용></주석>
		<주석><주석번호>015</주석번호><주석내용>거즛：거짓.</주석내용></주석>
		<주석><주석번호>016</주석번호><주석내용>혜：헤아림을.</주석내용></주석>
		<주석><주석번호>017</주석번호><주석내용>사니라：삼은 것이다.</주석내용></주석>
	</주석목록>

	<원본이미지목록>
	</원본이미지목록>
</내용>