<내용>
	<위치>
		<서명>역주 능엄경언해</서명>
		<단계명>역주 능엄경언해 제1</단계명>
		<단계명>[운허]Ⅱ. 정종분(正宗分)○첫째 사마타를 말하여 진심을 알게 하다 ①</단계명>
		<단계명>[운허]2. 견(見)이 곧 진심이다</단계명>
		<기사제목>4. 부처님이 답변하시다 1</기사제목>
	</위치>

	<본문>
		<기사>
			<구결><원본위치 imgFile="P15_NE_e01_v001_095a.jpg">능엄경언해 권1:95ㄱ</원본위치>二. 世尊答示 三○初. 光瑞開發〔경문〕 卽時如來ㅣ 從胸萬字샤 涌出寶光시니 其光이 晃昱샤 有百千色더시니 十方微塵普佛世界예 一時周徧샤 徧灌十方所有寶刹앳 諸如來頂시고 旋至阿難及諸大衆시니라</구결>
		</기사>
		<기사>
			<언해>〔경문〕 <원본위치 imgFile="P15_NE_e01_v001_095b.jpg">능엄경언해 권1:95ㄴ</원본위치>卽時예 如來 가맷 萬字 브트샤 보 光 소사내시니 그 光이 晃昱샤 百千色이 겨시더니 十方微塵 너븐 부텻 世界예   두루 펴샤 十方애 잇 寶刹앳 諸如來ㅅ 바기예 다 브시고 도로 阿難과 모 大衆의게 도라오시니라</언해>
		</기사>
		<기사>
			<번역문>〔경문〕 <sent lang="역주" n="1" page="v001_095b" type="main"/>즉시에 여래께서 가슴의 만자를 따르시어 보배의 광〈명〉을 솟아 내시니, <sent lang="역주" n="2" page="v001_095b" type="main"/>그 광명이 밝게 비치시어 백천색이 있더니, <sent lang="역주" n="3" page="v001_095b" type="main"/>시방 미진 넓은 부처님 세계에 일시에 두루 펴시어 <sent lang="역주" n="4" page="v001_095b" type="main"/>시방에 있는 보찰의 여러 여래의 정수리에 다 부으시고, <sent lang="역주" n="5" page="v001_095b" type="main"/>다시 아난과 모든 대중에게 돌아오신 것이다.</번역문>
		</기사>
		<기사>
			<구결>〔주해〕 將明眞見호려 샤 而從胸萬字샤 放寶光者 表由寶明妙心야 發正知見也ㅣ시니라 佛胸에 有卍字 表吉祥萬德의 所集이시니 其光이 晃然明며 昱然盛샤 有百千色샤 亦表妙心照用이 具足萬德也ㅣ시니라 光이 遍佛界者 示淸淨本然也ㅣ라 徧灌佛頂은 表極果所同也ㅣ라 旋及大衆은 示群靈이 共有也ㅣ라 此ㅣ 卽妙心道眼之眞光이시니 在聖야도 不增며 處凡야도 不減컨마 但隨量應現耳라</구결>
			</저자정보>
				<한글>세조(조선)</한글>
				<한자>世祖(朝鮮)</한자>
				<출판일>1461년(세조 7)</출판일>
			</저자정보>
		</기사>
		<기사>
			<언해>〔주해〕 <원본위치 imgFile="P15_NE_e01_v001_096a.jpg">능엄경언해 권1:96ㄱ</원본위치> 眞實ㅅ 보 교려 샤 가맷 萬字 브트샤 보 光을 펴샤 寶明妙心을 브터 正 知見 나 表시니라 부텻 가매 卍字ㅣ 겨샤 吉祥萬德<원본위치 imgFile="P15_NE_e01_v001_096b.jpg">능엄경언해 권1:96ㄴ</원본위치>의 모 고 表시니 그 光이 晃然히 며 昱然히 盛샤 百千色이 겨샤  妙心의 照用이 萬德이 조 表시니라 光이 佛界예 다 펴샤 淸淨 本然 뵈샤미라 부텻 바기예 다 브샤 至極 果ㅣ 가지샤 表시니라 大衆의게 도라오샤 群靈이 다 두쇼 뵈시니라 <협주>【群靈 衆生이니 性이 靈 靈이라 니라】</협주> 이 곧 妙心과 道眼 眞實ㅅ 光이시니 聖에 이셔도 더으디 아니며 凡에 이셔도 더디 아니컨마 오직 量 조차 應야 나 미라</언해>
			</저자정보>
				<한글>간경도감</한글>
				<한자>刊經都監</한자>
				<출판일>1462년(세조 8)</출판일>
			</저자정보>
		</기사>
		<기사>
			<번역문>〔주해〕 <sent lang="역주" n="1" page="v001_096a" type="anno"/>장차 진실한 보는 것을 밝히려 하셔서 가슴의 만자를 따르시어 <sent lang="역주" n="2" page="v001_096a" type="anno"/>보배의 광〈명〉을 펴심은 보명묘심을 말미암아 바른 지견 나는 것을 표하신 것이다. <sent lang="역주" n="3" page="v001_096a" type="anno"/>부처님의 가슴에 卍자가 계심은 길상〈과〉 만덕<sent lang="역주" n="1" page="v001_096b" type="anno"/>의 모인 것을 표하시니, 그 광〈명〉이 황연히 밝으며 욱연히 성하시어 <sent lang="역주" n="2" page="v001_096b" type="anno"/>백·천의 색이 계심은 또 묘심의 조용이 만덕이 구비함을 표하신 것이다. <sent lang="역주" n="3" page="v001_096b" type="anno"/>광〈명〉이 불계에 다 펴〈지〉심은 청정한 본연을 보이신 것이다. <sent lang="역주" n="4" page="v001_096b" type="anno"/>부처님의 정수리에 다 부으심은 지극한 ‘과’가 한가지 이심을 표하신 것이다. <sent lang="역주" n="5" page="v001_096b" type="anno"/>대중에게 돌아오신 것은 군령이 다 두었음을 보이신 것이다. <sent lang="역주" n="6" page="v001_096b" type="anno2"/><협주>【군령은 중생이니, 〈심〉성이 〈신〉령하므로 ‘영’이라 한 것이다.】</협주> <sent lang="역주" n="7" page="v001_096b" type="anno"/>이것이 묘심과 도안의 진실한 광〈명〉이시니, ‘성’〈의 자리에〉 있어도 더하지 아니하며, <sent lang="역주" n="8" page="v001_096b" type="anno"/>‘범’〈의 자리에〉 있어도 덜하지 아니하건마는 오직 ‘양’을 따라서 ‘응’하여 나타날 따름이다.</번역문>
			</저자정보>
				<한글>김영배</한글>
				<한자>金英培</한자>
				<출판일>1996년 9월 22일</출판일>
			</저자정보>
		</기사>
	</본문>

	<주석목록>
		<주석><주석번호>001</주석번호><주석내용>가맷：가슴에 있는. 가슴의. 「가」.</주석내용></주석>
		<주석><주석번호>002</주석번호><주석내용>보：보배의.</주석내용></주석>
		<주석><주석번호>003</주석번호><주석내용>황욱：밝게 빛남.</주석내용></주석>
		<주석><주석번호>004</주석번호><주석내용>너븐：넓은. 「넙-」.</주석내용></주석>
		<주석><주석번호>005</주석번호><주석내용> ：한 때에. 함께.</주석내용></주석>
		<주석><주석번호>006</주석번호><주석내용>바기예：정수리에.</주석내용></주석>
		<주석><주석번호>007</주석번호><주석내용>브시고：부으시고. 「-」[注].</주석내용></주석>
		<주석><주석번호>008</주석번호><주석내용>-의게：-에게.</주석내용></주석>
		<주석><주석번호>009</주석번호><주석내용>보찰：절. 부처님 계신 곳을 높여 부른 것.</주석내용></주석>
		<주석><주석번호>010</주석번호><주석내용>교려：밝히려. 「기-+오/우+려」.</주석내용></주석>
		<주석><주석번호>011</주석번호><주석내용>브트샤：붙으시어. 따라서.</주석내용></주석>
		<주석><주석번호>012</주석번호><주석내용>브터：붙어. 말미암아.</주석내용></주석>
		<주석><주석번호>013</주석번호><주석내용>겨샤：계심은. 「겨시-+오/우ㅁ → 겨샴」.</주석내용></주석>
		<주석><주석번호>014</주석번호><주석내용>모：모인. 「몯-」.</주석내용></주석>
		<주석><주석번호>015</주석번호><주석내용>고：곳을. 것을.</주석내용></주석>
		<주석><주석번호>016</주석번호><주석내용>조：구비함을. 「-」.</주석내용></주석>
		<주석><주석번호>017</주석번호><주석내용>뵈샤미라：보이심이다.</주석내용></주석>
		<주석><주석번호>018</주석번호><주석내용>브샤：부으심은. 「븟-~-」.</주석내용></주석>
		<주석><주석번호>019</주석번호><주석내용>가지샤：한가지심을.</주석내용></주석>
		<주석><주석번호>020</주석번호><주석내용>-의게：-에게.</주석내용></주석>
		<주석><주석번호>021</주석번호><주석내용>두쇼：두어 있음을. 「두시-+오/우ㅁ+」 「뒷-~두시-」.</주석내용></주석>
		<주석><주석번호>022</주석번호><주석내용>니라：하니라. 한 것이다.</주석내용></주석>
		<주석><주석번호>023</주석번호><주석내용>이：이것이.</주석내용></주석>
		<주석><주석번호>024</주석번호><주석내용>-：-의.</주석내용></주석>
		<주석><주석번호>025</주석번호><주석내용>이셔도：있어도. 「이시-」.</주석내용></주석>
		<주석><주석번호>026</주석번호><주석내용>더으디：더하지. 「더으-」.</주석내용></주석>
		<주석><주석번호>027</주석번호><주석내용>더디：덜지. 「덜-」.</주석내용></주석>
		<주석><주석번호>028</주석번호><주석내용>나：나타날. 「낟-」.</주석내용></주석>
		<주석><주석번호>029</주석번호><주석내용>미라：따름이다.</주석내용></주석>
		<주석><주석번호>030</주석번호><주석내용>보명묘심：보배롭고 밝은 미묘한 마음.</주석내용></주석>
		<주석><주석번호>031</주석번호><주석내용>지견：사리(事理)를 증지(證知)하는 견해.</주석내용></주석>
		<주석><주석번호>032</주석번호><주석내용>卍자：온갖 덕이 길상(吉祥)하다는 뜻.</주석내용></주석>
		<주석><주석번호>033</주석번호><주석내용>황연：환하게 밝은 모양.</주석내용></주석>
		<주석><주석번호>034</주석번호><주석내용>욱연：밝은 모양.</주석내용></주석>
		<주석><주석번호>035</주석번호><주석내용>청정：나쁜 짓으로 지은 허물이나 번뇌의 더러움에서 벗어난 깨끗함.</주석내용></주석>
		<주석><주석번호>036</주석번호><주석내용>성：성인의 경지.</주석내용></주석>
		<주석><주석번호>037</주석번호><주석내용>범：범속한 이의 경지.</주석내용></주석>
	</주석목록>

	<원본이미지목록>
	</원본이미지목록>
</내용>